nanoranker/__init__.py
nanoranker/resources/reranker_nn_v2_state_dict.pth
nanoranker/resources/universal-sentence-encoder-multilingual.onnx
nanoranker-1.1.dist-info/LICENSE
nanoranker-1.1.dist-info/METADATA
nanoranker-1.1.dist-info/WHEEL
nanoranker-1.1.dist-info/top_level.txt
nanoranker-1.1.dist-info/RECORD
