Metadata-Version: 2.1
Name: nanoranker
Version: 1.1
Author: Carlo Moro
Author-email: Carlo Moro <cnmoro@gmail.com>
Classifier: Programming Language :: Python :: 3
Classifier: License :: OSI Approved :: MIT License
Classifier: Operating System :: OS Independent
Requires-Python: >=3.7
License-File: LICENSE
Requires-Dist: torch
Requires-Dist: scikit-learn
Requires-Dist: tqdm
Requires-Dist: numpy
Requires-Dist: onnxruntime
Requires-Dist: onnxruntime-extensions
